git_bayesect.py
git_bayesect-1.0.dist-info/entry_points.txt
git_bayesect-1.0.dist-info/licenses/LICENSE
git_bayesect-1.0.dist-info/WHEEL
git_bayesect-1.0.dist-info/METADATA
git_bayesect-1.0.dist-info/RECORD
