Metadata-Version: 2.4
Name: git_bayesect
Version: 1.0
Summary: Git bisection with Bayesian statistics
Author: Shantanu Jain
Author-email: hauntsaninja@gmail.com
Requires-Python: >=3.10
Classifier: Intended Audience :: Developers
Classifier: License :: OSI Approved :: MIT License
Classifier: Operating System :: OS Independent
Classifier: Programming Language :: Python :: 3
Classifier: Topic :: Software Development
Classifier: Topic :: Utilities
License-File: LICENSE
Requires-Dist: numpy
Requires-Dist: scipy
Project-URL: homepage, https://github.com/hauntsaninja/git_bayesect
Project-URL: repository, https://github.com/hauntsaninja/git_bayesect
